main.py
mpk/__init__.py
mpk/_mpk.c
mpk/_mpk.cpython-39-darwin.so
mpk/_mpk.o
mpk/extract.py
mpk/lib.py
mpk/libmpk_ffi.dylib
mpk-0.1.0a9.dist-info/entry_points.txt
mpk-0.1.0a9.dist-info/WHEEL
mpk-0.1.0a9.dist-info/METADATA
mpk-0.1.0a9.dist-info/RECORD
